Metadata-Version: 1.1
Name: golangish
Version: 0.0.5
Summary: Port Golang's CSP semantics to Python
Home-page: https://github.com/edouardklein/golangish
Author: Edouard Klein
Author-email: myfirstnamemylastname@mailproviderthatstartswithagfromgoogle.whyshouldibespammed.letmeinputhateveriwantinthisfieldffs.com
License: AGPLv3
Download-URL: https://github.com/edouardklein/golangish/tarball/0.0.5
Keywords: CSP,Golang,Channel,Coroutine,Select
Platform: UNKNOWN
Classifier: Development Status :: 3 - Alpha
Classifier: Framework :: AsyncIO
Classifier: Intended Audience :: Developers
Classifier: License :: OSI Approved :: GNU Affero General Public License v3 or later (AGPLv3+)
Classifier: Operating System :: POSIX
Classifier: Programming Language :: Python :: 3.6
